{"box_data": [{"position": {"minX": 271.25, "minY": 162.375, "maxX": 285.25, "maxY": 227.875}, "class_id": 0, "box_caption": "hole 0.144", "scores": {"class_score": 0.1439208984375}, "domain": "pixel"}, {"position": {"minX": 442.75, "minY": 424.5, "maxX": 473.25, "maxY": 514.5}, "class_id": 0, "box_caption": "hole 0.002", "scores": {"class_score": 0.00177001953125}, "domain": "pixel"}, {"position": {"minX": 268.25, "minY": 166.5, "maxX": 282.25, "maxY": 225.0}, "class_id": 0, "box_caption": "hole 0.001", "scores": {"class_score": 0.001499176025390625}, "domain": "pixel"}, {"position": {"minX": 418.75, "minY": 567.5, "maxX": 437.25, "maxY": 624.5}, "class_id": 0, "box_caption": "hole 0.001", "scores": {"class_score": 0.0012140274047851562}, "domain": "pixel"}], "class_labels": {"0": "hole", "1": "stain"}}