{"box_data": [{"position": {"minX": 313.5, "minY": 159.25, "maxX": 328.5, "maxY": 204.5}, "class_id": 0, "box_caption": "hole 0.426", "scores": {"class_score": 0.42578125}, "domain": "pixel"}, {"position": {"minX": 312.75, "minY": 159.75, "maxX": 328.75, "maxY": 204.5}, "class_id": 1, "box_caption": "stain 0.311", "scores": {"class_score": 0.311279296875}, "domain": "pixel"}, {"position": {"minX": 77.0, "minY": 176.625, "maxX": 128.625, "maxY": 288.25}, "class_id": 0, "box_caption": "hole 0.003", "scores": {"class_score": 0.003021240234375}, "domain": "pixel"}, {"position": {"minX": 197.875, "minY": 16.328125, "maxX": 240.375, "maxY": 54.4375}, "class_id": 1, "box_caption": "stain 0.003", "scores": {"class_score": 0.0030117034912109375}, "domain": "pixel"}, {"position": {"minX": 434.25, "minY": 134.5, "maxX": 473.25, "maxY": 235.0}, "class_id": 0, "box_caption": "hole 0.002", "scores": {"class_score": 0.0023021697998046875}, "domain": "pixel"}, {"position": {"minX": 407.5, "minY": 5.796875, "maxX": 463.0, "maxY": 63.5625}, "class_id": 1, "box_caption": "stain 0.002", "scores": {"class_score": 0.0018682479858398438}, "domain": "pixel"}, {"position": {"minX": 419.5, "minY": 14.4375, "maxX": 470.5, "maxY": 61.0625}, "class_id": 1, "box_caption": "stain 0.002", "scores": {"class_score": 0.001773834228515625}, "domain": "pixel"}, {"position": {"minX": 165.25, "minY": 123.0625, "maxX": 208.0, "maxY": 257.0}, "class_id": 0, "box_caption": "hole 0.002", "scores": {"class_score": 0.001697540283203125}, "domain": "pixel"}, {"position": {"minX": 88.375, "minY": 15.640625, "maxX": 127.625, "maxY": 55.375}, "class_id": 1, "box_caption": "stain 0.002", "scores": {"class_score": 0.0016813278198242188}, "domain": "pixel"}, {"position": {"minX": 581.0, "minY": 15.234375, "maxX": 617.0, "maxY": 58.0}, "class_id": 1, "box_caption": "stain 0.001", "scores": {"class_score": 0.0013170242309570312}, "domain": "pixel"}, {"position": {"minX": 102.25, "minY": 15.71875, "maxX": 142.0, "maxY": 55.90625}, "class_id": 1, "box_caption": "stain 0.001", "scores": {"class_score": 0.0011501312255859375}, "domain": "pixel"}, {"position": {"minX": 394.0, "minY": -17.34375, "maxX": 491.5, "maxY": 93.5}, "class_id": 1, "box_caption": "stain 0.001", "scores": {"class_score": 0.0010995864868164062}, "domain": "pixel"}], "class_labels": {"0": "hole", "1": "stain"}}